cutmix_keras.py
cutmix_keras-1.0.0.dist-info/LICENSE
cutmix_keras-1.0.0.dist-info/METADATA
cutmix_keras-1.0.0.dist-info/WHEEL
cutmix_keras-1.0.0.dist-info/top_level.txt
cutmix_keras-1.0.0.dist-info/RECORD
