Metadata-Version: 2.1
Name: cutmix-keras
Version: 1.0.0
Summary: CutMuxImageDataGenerator For Keras
Home-page: https://github.com/DevBruce/CutMixImageDataGenerator_For_Keras
Author: devbruce
Author-email: bruce93k@gmail.com
License: MIT
Keywords: cutmix,keras
Platform: UNKNOWN
